{
    "metadata": {
        "dataVersion": "2",
        "matchId": "BR1_2419611997",
        "participants": [
            "1ABiDRR7JZeli0-oghFHEEYeFhmaeO-SVVMnySLysMuin9itS1Zuy2c5G65RdqoLksieRgtcC1jPLA",
            "9zamQP0gpiX29O8dP1G_t3ec2bbP-QrioPZGNAdYFdngIsTceyjE8_w2zPWUpfBcHqy2kWCtrhn2Jw",
            "09mnKdnn1r2Gjlh591p0FmXt0wFWY4YNuThn0vgD_YxIPFc3Is40uUK-COoWgoP-mhBGJ8gRDd-ANw",
            "OEzxgKw9YhlA5uZzJwm8N2IFMli-XJZma4IMQG0MeBFA81mdQCauIMk56i5F5co7w70sxmRluXhSSA",
            "t98mb1GtoDemGPKQRAOi0tmLFKIx1mQdpUVf0fuvkoOEFvp08PnxW6GjzKy53Mb-TU-wlQ0gzJzGsg",
            "EE5aE_cUHRK3Jtybd8n5FTH1Yx_zosqTAV_yscfg4TdGufm8jc6Fs99eVMxBEeVMAeJnI7MqGvWU0Q",
            "GNly6iOMNVfvlYRkqCjp7FGp8g2HAKYFBl5MGnH-_opTrJtNu1HF7VOMDFiKzx9rYDp1ACFxoeNo9w",
            "66NyRlrbkqV4S1IlflA7b7gtR9bdaikAWSbXsmaq6iua0k1oj25DlprwUIS3qZmHIo7Stf6aI64fIw",
            "UW3X7SlXHsN2YaQPT-nVc2qgj4AtcpQiBKz2ypwifdhnfumz5LhZDuW8X86OGZIjyx3shpXuTkJkXA",
            "eLT_SnTzJWb0T3VYMkrY3tkhbKg5mguEJjZZhh-Gn8Wp5YflPy_zS1pxKnpY-JQjnTMCKzJkJOYjSg"
        ]
    },
    "info": {
        "gameCreation": 1639700168000,
        "gameDuration": 1260,
        "gameEndTimestamp": 1639701549432,
        "gameId": 2419611997,
        "gameMode": "ARAM",
        "gameName": "teambuilder-match-2419611997",
        "gameStartTimestamp": 1639700289257,
        "gameType": "MATCHED_GAME",
        "gameVersion": "11.24.413.2485",
        "mapId": 12,
        "participants": [
            {
                "assists": 24,
                "baronKills": 0,
                "bountyLevel": 0,
                "champExperience": 19669,
                "champLevel": 18,
                "championId": 150,
                "championName": "Gnar",
                "championTransform": 0,
                "consumablesPurchased": 0,
                "damageDealtToBuildings": 709,
                "damageDealtToObjectives": 709,
                "damageDealtToTurrets": 709,
                "damageSelfMitigated": 29462,
                "deaths": 12,
                "detectorWardsPlaced": 0,
                "doubleKills": 1,
                "dragonKills": 0,
                "firstBloodAssist": false,
                "firstBloodKill": false,
                "firstTowerAssist": true,
                "firstTowerKill": false,
                "gameEndedInEarlySurrender": false,
                "gameEndedInSurrender": false,
                "goldEarned": 12839,
                "goldSpent": 12450,
                "individualPosition": "Invalid",
                "inhibitorKills": 0,
                "inhibitorTakedowns": 0,
                "inhibitorsLost": 0,
                "item0": 3091,
                "item1": 6631,
                "item2": 4401,
                "item3": 3211,
                "item4": 3111,
                "item5": 3067,
                "item6": 0,
                "itemsPurchased": 28,
                "killingSprees": 1,
                "kills": 3,
                "lane": "TOP",
                "largestCriticalStrike": 0,
                "largestKillingSpree": 2,
                "largestMultiKill": 2,
                "longestTimeSpentLiving": 138,
                "magicDamageDealt": 6602,
                "magicDamageDealtToChampions": 1946,
                "magicDamageTaken": 18796,
                "neutralMinionsKilled": 0,
                "nexusKills": 0,
                "nexusLost": 0,
                "nexusTakedowns": 0,
                "objectivesStolen": 0,
                "objectivesStolenAssists": 0,
                "participantId": 1,
                "pentaKills": 0,
                "perks": {
                    "statPerks": {
                        "defense": 5002,
                        "flex": 5008,
                        "offense": 5005
                    },
                    "styles": [
                        {
                            "description": "primaryStyle",
                            "selections": [
                                {
                                    "perk": 8008,
                                    "var1": 25,
                                    "var2": 3,
                                    "var3": 0
                                },
                                {
                                    "perk": 9111,
                                    "var1": 854,
                                    "var2": 270,
                                    "var3": 0
                                },
                                {
                                    "perk": 9105,
                                    "var1": 10,
                                    "var2": 10,
                                    "var3": 0
                                },
                                {
                                    "perk": 8299,
                                    "var1": 624,
                                    "var2": 0,
                                    "var3": 0
                                }
                            ],
                            "style": 8000
                        },
                        {
                            "description": "subStyle",
                            "selections": [
                                {
                                    "perk": 8473,
                                    "var1": 978,
                                    "var2": 0,
                                    "var3": 0
                                },
                                {
                                    "perk": 8242,
                                    "var1": 141,
                                    "var2": 0,
                                    "var3": 0
                                }
                            ],
                            "style": 8400
                        }
                    ]
                },
                "physicalDamageDealt": 47240,
                "physicalDamageDealtToChampions": 12766,
                "physicalDamageTaken": 6256,
                "profileIcon": 5089,
                "puuid": "1ABiDRR7JZeli0-oghFHEEYeFhmaeO-SVVMnySLysMuin9itS1Zuy2c5G65RdqoLksieRgtcC1jPLA",
                "quadraKills": 0,
                "riotIdName": "",
                "riotIdTagline": "",
                "role": "SUPPORT",
                "sightWardsBoughtInGame": 0,
                "spell1Casts": 60,
                "spell2Casts": 11,
                "spell3Casts": 16,
                "spell4Casts": 6,
                "summoner1Casts": 4,
                "summoner1Id": 3,
                "summoner2Casts": 5,
                "summoner2Id": 4,
                "summonerId": "k_0-3tXyp2HrRhkTp9mO51L5O5iTkbI9CPecEXzVgdEabakQeP4_Z8GoGg",
                "summonerLevel": 211,
                "summonerName": "daneuuh",
                "teamEarlySurrendered": false,
                "teamId": 100,
                "teamPosition": "",
                "timeCCingOthers": 24,
                "timePlayed": 1260,
                "totalDamageDealt": 53842,
                "totalDamageDealtToChampions": 14712,
                "totalDamageShieldedOnTeammates": 0,
                "totalDamageTaken": 26530,
                "totalHeal": 1465,
                "totalHealsOnTeammates": 0,
                "totalMinionsKilled": 57,
                "totalTimeCCDealt": 317,
                "totalTimeSpentDead": 328,
                "totalUnitsHealed": 1,
                "tripleKills": 0,
                "trueDamageDealt": 0,
                "trueDamageDealtToChampions": 0,
                "trueDamageTaken": 1478,
                "turretKills": 0,
                "turretTakedowns": 1,
                "turretsLost": 1,
                "unrealKills": 0,
                "visionScore": 0,
                "visionWardsBoughtInGame": 0,
                "wardsKilled": 0,
                "wardsPlaced": 0,
                "win": true
            },
            {
                "assists": 18,
                "baronKills": 0,
                "bountyLevel": 0,
                "champExperience": 26519,
                "champLevel": 18,
                "championId": 51,
                "championName": "Caitlyn",
                "championTransform": 0,
                "consumablesPurchased": 1,
                "damageDealtToBuildings": 2990,
                "damageDealtToObjectives": 2990,
                "damageDealtToTurrets": 2990,
                "damageSelfMitigated": 6956,
                "deaths": 8,
                "detectorWardsPlaced": 0,
                "doubleKills": 4,
                "dragonKills": 0,
                "firstBloodAssist": false,
                "firstBloodKill": false,
                "firstTowerAssist": true,
                "firstTowerKill": false,
                "gameEndedInEarlySurrender": false,
                "gameEndedInSurrender": false,
                "goldEarned": 18456,
                "goldSpent": 16250,
                "individualPosition": "Invalid",
                "inhibitorKills": 1,
                "inhibitorTakedowns": 1,
                "inhibitorsLost": 0,
                "item0": 6691,
                "item1": 3158,
                "item2": 6676,
                "item3": 3814,
                "item4": 3156,
                "item5": 6696,
                "item6": 2052,
                "itemsPurchased": 18,
                "killingSprees": 6,
                "kills": 24,
                "lane": "TOP",
                "largestCriticalStrike": 640,
                "largestKillingSpree": 7,
                "largestMultiKill": 2,
                "longestTimeSpentLiving": 237,
                "magicDamageDealt": 1362,
                "magicDamageDealtToChampions": 1190,
                "magicDamageTaken": 11334,
                "neutralMinionsKilled": 0,
                "nexusKills": 0,
                "nexusLost": 0,
                "nexusTakedowns": 0,
                "objectivesStolen": 0,
                "objectivesStolenAssists": 0,
                "participantId": 2,
                "pentaKills": 0,
                "perks": {
                    "statPerks": {
                        "defense": 5002,
                        "flex": 5008,
                        "offense": 5007
                    },
                    "styles": [
                        {
                            "description": "primaryStyle",
                            "selections": [
                                {
                                    "perk": 8128,
                                    "var1": 2516,
                                    "var2": 32,
                                    "var3": 0
                                },
                                {
                                    "perk": 8126,
                                    "var1": 1020,
                                    "var2": 0,
                                    "var3": 0
                                },
                                {
                                    "perk": 8138,
                                    "var1": 18,
                                    "var2": 0,
                                    "var3": 0
                                },
                                {
                                    "perk": 8106,
                                    "var1": 5,
                                    "var2": 0,
                                    "var3": 0
                                }
                            ],
                            "style": 8100
                        },
                        {
                            "description": "subStyle",
                            "selections": [
                                {
                                    "perk": 8226,
                                    "var1": 250,
                                    "var2": 766,
                                    "var3": 0
                                },
                                {
                                    "perk": 8236,
                                    "var1": 28,
                                    "var2": 0,
                                    "var3": 0
                                }
                            ],
                            "style": 8200
                        }
                    ]
                },
                "physicalDamageDealt": 82889,
                "physicalDamageDealtToChampions": 45725,
                "physicalDamageTaken": 2092,
                "profileIcon": 1456,
                "puuid": "9zamQP0gpiX29O8dP1G_t3ec2bbP-QrioPZGNAdYFdngIsTceyjE8_w2zPWUpfBcHqy2kWCtrhn2Jw",
                "quadraKills": 0,
                "riotIdName": "",
                "riotIdTagline": "",
                "role": "SUPPORT",
                "sightWardsBoughtInGame": 0,
                "spell1Casts": 57,
                "spell2Casts": 58,
                "spell3Casts": 25,
                "spell4Casts": 19,
                "summoner1Casts": 5,
                "summoner1Id": 21,
                "summoner2Casts": 2,
                "summoner2Id": 4,
                "summonerId": "JUo2h5EpzJu9mTeZzYSkT5FnMVk-ZT73sCl7Vqb6p0zo7BU",
                "summonerLevel": 166,
                "summonerName": "Coala REAL CRIA",
                "teamEarlySurrendered": false,
                "teamId": 100,
                "teamPosition": "",
                "timeCCingOthers": 49,
                "timePlayed": 1260,
                "totalDamageDealt": 85382,
                "totalDamageDealtToChampions": 48045,
                "totalDamageShieldedOnTeammates": 0,
                "totalDamageTaken": 13988,
                "totalHeal": 404,
                "totalHealsOnTeammates": 0,
                "totalMinionsKilled": 46,
                "totalTimeCCDealt": 81,
                "totalTimeSpentDead": 168,
                "totalUnitsHealed": 1,
                "tripleKills": 0,
                "trueDamageDealt": 1130,
                "trueDamageDealtToChampions": 1130,
                "trueDamageTaken": 562,
                "turretKills": 1,
                "turretTakedowns": 3,
                "turretsLost": 1,
                "unrealKills": 0,
                "visionScore": 0,
                "visionWardsBoughtInGame": 0,
                "wardsKilled": 0,
                "wardsPlaced": 0,
                "win": true
            },
            {
                "assists": 25,
                "baronKills": 0,
                "bountyLevel": 0,
                "champExperience": 20408,
                "champLevel": 18,
                "championId": 133,
                "championName": "Quinn",
                "championTransform": 0,
                "consumablesPurchased": 6,
                "damageDealtToBuildings": 2008,
                "damageDealtToObjectives": 2008,
                "damageDealtToTurrets": 2008,
                "damageSelfMitigated": 23516,
                "deaths": 10,
                "detectorWardsPlaced": 0,
                "doubleKills": 0,
                "dragonKills": 0,
                "firstBloodAssist": true,
                "firstBloodKill": false,
                "firstTowerAssist": false,
                "firstTowerKill": true,
                "gameEndedInEarlySurrender": false,
                "gameEndedInSurrender": false,
                "goldEarned": 13125,
                "goldSpent": 12250,
                "individualPosition": "Invalid",
                "inhibitorKills": 0,
                "inhibitorTakedowns": 1,
                "inhibitorsLost": 0,
                "item0": 6673,
                "item1": 3072,
                "item2": 3006,
                "item3": 3091,
                "item4": 3184,
                "item5": 0,
                "item6": 2052,
                "itemsPurchased": 27,
                "killingSprees": 0,
                "kills": 4,
                "lane": "TOP",
                "largestCriticalStrike": 387,
                "largestKillingSpree": 0,
                "largestMultiKill": 1,
                "longestTimeSpentLiving": 221,
                "magicDamageDealt": 4194,
                "magicDamageDealtToChampions": 531,
                "magicDamageTaken": 22508,
                "neutralMinionsKilled": 0,
                "nexusKills": 0,
                "nexusLost": 0,
                "nexusTakedowns": 0,
                "objectivesStolen": 0,
                "objectivesStolenAssists": 0,
                "participantId": 3,
                "pentaKills": 0,
                "perks": {
                    "statPerks": {
                        "defense": 5001,
                        "flex": 5008,
                        "offense": 5005
                    },
                    "styles": [
                        {
                            "description": "primaryStyle",
                            "selections": [
                                {
                                    "perk": 8005,
                                    "var1": 877,
                                    "var2": 582,
                                    "var3": 294
                                },
                                {
                                    "perk": 9111,
                                    "var1": 1380,
                                    "var2": 290,
                                    "var3": 0
                                },
                                {
                                    "perk": 9104,
                                    "var1": 4,
                                    "var2": 40,
                                    "var3": 0
                                },
                                {
                                    "perk": 8017,
                                    "var1": 410,
                                    "var2": 0,
                                    "var3": 0
                                }
                            ],
                            "style": 8000
                        },
                        {
                            "description": "subStyle",
                            "selections": [
                                {
                                    "perk": 8135,
                                    "var1": 3062,
                                    "var2": 5,
                                    "var3": 0
                                },
                                {
                                    "perk": 8143,
                                    "var1": 455,
                                    "var2": 0,
                                    "var3": 0
                                }
                            ],
                            "style": 8100
                        }
                    ]
                },
                "physicalDamageDealt": 58043,
                "physicalDamageDealtToChampions": 19788,
                "physicalDamageTaken": 7778,
                "profileIcon": 775,
                "puuid": "09mnKdnn1r2Gjlh591p0FmXt0wFWY4YNuThn0vgD_YxIPFc3Is40uUK-COoWgoP-mhBGJ8gRDd-ANw",
                "quadraKills": 0,
                "riotIdName": "",
                "riotIdTagline": "",
                "role": "SUPPORT",
                "sightWardsBoughtInGame": 0,
                "spell1Casts": 39,
                "spell2Casts": 11,
                "spell3Casts": 29,
                "spell4Casts": 12,
                "summoner1Casts": 5,
                "summoner1Id": 4,
                "summoner2Casts": 8,
                "summoner2Id": 21,
                "summonerId": "bBxz5exXXDAKZ32YM_LPrrIT4_HXUhDOFngt9caxpb_IR-o",
                "summonerLevel": 350,
                "summonerName": "Uno Mille 1997",
                "teamEarlySurrendered": false,
                "teamId": 100,
                "teamPosition": "",
                "timeCCingOthers": 34,
                "timePlayed": 1260,
                "totalDamageDealt": 65447,
                "totalDamageDealtToChampions": 20320,
                "totalDamageShieldedOnTeammates": 0,
                "totalDamageTaken": 32103,
                "totalHeal": 2485,
                "totalHealsOnTeammates": 0,
                "totalMinionsKilled": 48,
                "totalTimeCCDealt": 87,
                "totalTimeSpentDead": 270,
                "totalUnitsHealed": 1,
                "tripleKills": 0,
                "trueDamageDealt": 3210,
                "trueDamageDealtToChampions": 0,
                "trueDamageTaken": 1817,
                "turretKills": 1,
                "turretTakedowns": 4,
                "turretsLost": 1,
                "unrealKills": 0,
                "visionScore": 2,
                "visionWardsBoughtInGame": 0,
                "wardsKilled": 0,
                "wardsPlaced": 0,
                "win": true
            },
            {
                "assists": 12,
                "baronKills": 0,
                "bountyLevel": 1,
                "champExperience": 19079,
                "champLevel": 18,
                "championId": 107,
                "championName": "Rengar",
                "championTransform": 0,
                "consumablesPurchased": 0,
                "damageDealtToBuildings": 3235,
                "damageDealtToObjectives": 3235,
                "damageDealtToTurrets": 3235,
                "damageSelfMitigated": 11391,
                "deaths": 10,
                "detectorWardsPlaced": 0,
                "doubleKills": 1,
                "dragonKills": 0,
                "firstBloodAssist": true,
                "firstBloodKill": false,
                "firstTowerAssist": true,
                "firstTowerKill": false,
                "gameEndedInEarlySurrender": false,
                "gameEndedInSurrender": false,
                "goldEarned": 14657,
                "goldSpent": 14400,
                "individualPosition": "Invalid",
                "inhibitorKills": 0,
                "inhibitorTakedowns": 0,
                "inhibitorsLost": 0,
                "item0": 6691,
                "item1": 3142,
                "item2": 6696,
                "item3": 3158,
                "item4": 3814,
                "item5": 3035,
                "item6": 2052,
                "itemsPurchased": 17,
                "killingSprees": 5,
                "kills": 15,
                "lane": "TOP",
                "largestCriticalStrike": 0,
                "largestKillingSpree": 3,
                "largestMultiKill": 2,
                "longestTimeSpentLiving": 232,
                "magicDamageDealt": 4007,
                "magicDamageDealtToChampions": 2567,
                "magicDamageTaken": 19010,
                "neutralMinionsKilled": 0,
                "nexusKills": 0,
                "nexusLost": 0,
                "nexusTakedowns": 0,
                "objectivesStolen": 0,
                "objectivesStolenAssists": 0,
                "participantId": 4,
                "pentaKills": 0,
                "perks": {
                    "statPerks": {
                        "defense": 5003,
                        "flex": 5008,
                        "offense": 5005
                    },
                    "styles": [
                        {
                            "description": "primaryStyle",
                            "selections": [
                                {
                                    "perk": 8112,
                                    "var1": 940,
                                    "var2": 0,
                                    "var3": 0
                                },
                                {
                                    "perk": 8143,
                                    "var1": 738,
                                    "var2": 0,
                                    "var3": 0
                                },
                                {
                                    "perk": 8138,
                                    "var1": 18,
                                    "var2": 0,
                                    "var3": 0
                                },
                                {
                                    "perk": 8135,
                                    "var1": 1123,
                                    "var2": 5,
                                    "var3": 0
                                }
                            ],
                            "style": 8100
                        },
                        {
                            "description": "subStyle",
                            "selections": [
                                {
                                    "perk": 9104,
                                    "var1": 9,
                                    "var2": 10,
                                    "var3": 0
                                },
                                {
                                    "perk": 8014,
                                    "var1": 814,
                                    "var2": 0,
                                    "var3": 0
                                }
                            ],
                            "style": 8000
                        }
                    ]
                },
                "physicalDamageDealt": 35417,
                "physicalDamageDealtToChampions": 19600,
                "physicalDamageTaken": 3516,
                "profileIcon": 5091,
                "puuid": "OEzxgKw9YhlA5uZzJwm8N2IFMli-XJZma4IMQG0MeBFA81mdQCauIMk56i5F5co7w70sxmRluXhSSA",
                "quadraKills": 0,
                "riotIdName": "",
                "riotIdTagline": "",
                "role": "SUPPORT",
                "sightWardsBoughtInGame": 0,
                "spell1Casts": 54,
                "spell2Casts": 34,
                "spell3Casts": 54,
                "spell4Casts": 9,
                "summoner1Casts": 15,
                "summoner1Id": 32,
                "summoner2Casts": 3,
                "summoner2Id": 4,
                "summonerId": "Qt_N7GpAR2QebHqic0sE9ACgZQM1LneYuRvXontTS5kxP_o",
                "summonerLevel": 166,
                "summonerName": "CheveteMaraj\u00f383",
                "teamEarlySurrendered": false,
                "teamId": 100,
                "teamPosition": "",
                "timeCCingOthers": 9,
                "timePlayed": 1260,
                "totalDamageDealt": 40100,
                "totalDamageDealtToChampions": 22788,
                "totalDamageShieldedOnTeammates": 0,
                "totalDamageTaken": 23535,
                "totalHeal": 4675,
                "totalHealsOnTeammates": 0,
                "totalMinionsKilled": 27,
                "totalTimeCCDealt": 38,
                "totalTimeSpentDead": 280,
                "totalUnitsHealed": 1,
                "tripleKills": 0,
                "trueDamageDealt": 675,
                "trueDamageDealtToChampions": 620,
                "trueDamageTaken": 1008,
                "turretKills": 1,
                "turretTakedowns": 3,
                "turretsLost": 1,
                "unrealKills": 0,
                "visionScore": 0,
                "visionWardsBoughtInGame": 0,
                "wardsKilled": 0,
                "wardsPlaced": 0,
                "win": true
            },
            {
                "assists": 15,
                "baronKills": 0,
                "bountyLevel": 0,
                "champExperience": 22014,
                "champLevel": 18,
                "championId": 121,
                "championName": "Khazix",
                "championTransform": 0,
                "consumablesPurchased": 3,
                "damageDealtToBuildings": 608,
                "damageDealtToObjectives": 608,
                "damageDealtToTurrets": 608,
                "damageSelfMitigated": 15219,
                "deaths": 11,
                "detectorWardsPlaced": 0,
                "doubleKills": 1,
                "dragonKills": 0,
                "firstBloodAssist": false,
                "firstBloodKill": true,
                "firstTowerAssist": false,
                "firstTowerKill": false,
                "gameEndedInEarlySurrender": false,
                "gameEndedInSurrender": false,
                "goldEarned": 14043,
                "goldSpent": 12450,
                "individualPosition": "Invalid",
                "inhibitorKills": 0,
                "inhibitorTakedowns": 1,
                "inhibitorsLost": 0,
                "item0": 6691,
                "item1": 3111,
                "item2": 6676,
                "item3": 3814,
                "item4": 3134,
                "item5": 3133,
                "item6": 0,
                "itemsPurchased": 22,
                "killingSprees": 4,
                "kills": 11,
                "lane": "TOP",
                "largestCriticalStrike": 422,
                "largestKillingSpree": 3,
                "largestMultiKill": 2,
                "longestTimeSpentLiving": 217,
                "magicDamageDealt": 1100,
                "magicDamageDealtToChampions": 1100,
                "magicDamageTaken": 18482,
                "neutralMinionsKilled": 0,
                "nexusKills": 1,
                "nexusLost": 0,
                "nexusTakedowns": 1,
                "objectivesStolen": 0,
                "objectivesStolenAssists": 0,
                "participantId": 5,
                "pentaKills": 0,
                "perks": {
                    "statPerks": {
                        "defense": 5002,
                        "flex": 5008,
                        "offense": 5008
                    },
                    "styles": [
                        {
                            "description": "primaryStyle",
                            "selections": [
                                {
                                    "perk": 8128,
                                    "var1": 1363,
                                    "var2": 21,
                                    "var3": 0
                                },
                                {
                                    "perk": 8143,
                                    "var1": 529,
                                    "var2": 0,
                                    "var3": 0
                                },
                                {
                                    "perk": 8138,
                                    "var1": 18,
                                    "var2": 0,
                                    "var3": 0
                                },
                                {
                                    "perk": 8135,
                                    "var1": 1303,
                                    "var2": 5,
                                    "var3": 0
                                }
                            ],
                            "style": 8100
                        },
                        {
                            "description": "subStyle",
                            "selections": [
                                {
                                    "perk": 8009,
                                    "var1": 2427,
                                    "var2": 0,
                                    "var3": 0
                                },
                                {
                                    "perk": 8014,
                                    "var1": 696,
                                    "var2": 0,
                                    "var3": 0
                                }
                            ],
                            "style": 8000
                        }
                    ]
                },
                "physicalDamageDealt": 39119,
                "physicalDamageDealtToChampions": 20827,
                "physicalDamageTaken": 2980,
                "profileIcon": 5193,
                "puuid": "t98mb1GtoDemGPKQRAOi0tmLFKIx1mQdpUVf0fuvkoOEFvp08PnxW6GjzKy53Mb-TU-wlQ0gzJzGsg",
                "quadraKills": 0,
                "riotIdName": "",
                "riotIdTagline": "",
                "role": "SUPPORT",
                "sightWardsBoughtInGame": 0,
                "spell1Casts": 18,
                "spell2Casts": 56,
                "spell3Casts": 25,
                "spell4Casts": 15,
                "summoner1Casts": 6,
                "summoner1Id": 4,
                "summoner2Casts": 17,
                "summoner2Id": 32,
                "summonerId": "gS-qpERb_AdbGvAOerFZ83O5qHd9RVPkb7XwtE-8JFMW5gY",
                "summonerLevel": 225,
                "summonerName": "Mist Ahri",
                "teamEarlySurrendered": false,
                "teamId": 100,
                "teamPosition": "",
                "timeCCingOthers": 14,
                "timePlayed": 1260,
                "totalDamageDealt": 41386,
                "totalDamageDealtToChampions": 23068,
                "totalDamageShieldedOnTeammates": 0,
                "totalDamageTaken": 22092,
                "totalHeal": 2878,
                "totalHealsOnTeammates": 0,
                "totalMinionsKilled": 18,
                "totalTimeCCDealt": 258,
                "totalTimeSpentDead": 238,
                "totalUnitsHealed": 1,
                "tripleKills": 0,
                "trueDamageDealt": 1165,
                "trueDamageDealtToChampions": 1140,
                "trueDamageTaken": 630,
                "turretKills": 1,
                "turretTakedowns": 2,
                "turretsLost": 1,
                "unrealKills": 0,
                "visionScore": 0,
                "visionWardsBoughtInGame": 0,
                "wardsKilled": 0,
                "wardsPlaced": 0,
                "win": true
            },
            {
                "assists": 22,
                "baronKills": 0,
                "bountyLevel": 1,
                "champExperience": 19409,
                "champLevel": 18,
                "championId": 45,
                "championName": "Veigar",
                "championTransform": 0,
                "consumablesPurchased": 2,
                "damageDealtToBuildings": 884,
                "damageDealtToObjectives": 884,
                "damageDealtToTurrets": 884,
                "damageSelfMitigated": 16884,
                "deaths": 12,
                "detectorWardsPlaced": 0,
                "doubleKills": 0,
                "dragonKills": 0,
                "firstBloodAssist": false,
                "firstBloodKill": false,
                "firstTowerAssist": false,
                "firstTowerKill": false,
                "gameEndedInEarlySurrender": false,
                "gameEndedInSurrender": false,
                "goldEarned": 12392,
                "goldSpent": 11500,
                "individualPosition": "Invalid",
                "inhibitorKills": 0,
                "inhibitorTakedowns": 0,
                "inhibitorsLost": 1,
                "item0": 2031,
                "item1": 3157,
                "item2": 6655,
                "item3": 3020,
                "item4": 3089,
                "item5": 4632,
                "item6": 2052,
                "itemsPurchased": 16,
                "killingSprees": 0,
                "kills": 5,
                "lane": "TOP",
                "largestCriticalStrike": 0,
                "largestKillingSpree": 0,
                "largestMultiKill": 1,
                "longestTimeSpentLiving": 124,
                "magicDamageDealt": 46772,
                "magicDamageDealtToChampions": 16009,
                "magicDamageTaken": 882,
                "neutralMinionsKilled": 0,
                "nexusKills": 0,
                "nexusLost": 1,
                "nexusTakedowns": 0,
                "objectivesStolen": 0,
                "objectivesStolenAssists": 0,
                "participantId": 6,
                "pentaKills": 0,
                "perks": {
                    "statPerks": {
                        "defense": 5002,
                        "flex": 5003,
                        "offense": 5007
                    },
                    "styles": [
                        {
                            "description": "primaryStyle",
                            "selections": [
                                {
                                    "perk": 8229,
                                    "var1": 1116,
                                    "var2": 0,
                                    "var3": 0
                                },
                                {
                                    "perk": 8226,
                                    "var1": 250,
                                    "var2": 696,
                                    "var3": 0
                                },
                                {
                                    "perk": 8210,
                                    "var1": 15,
                                    "var2": 0,
                                    "var3": 0
                                },
                                {
                                    "perk": 8237,
                                    "var1": 425,
                                    "var2": 0,
                                    "var3": 0
                                }
                            ],
                            "style": 8200
                        },
                        {
                            "description": "subStyle",
                            "selections": [
                                {
                                    "perk": 8313,
                                    "var1": 0,
                                    "var2": 0,
                                    "var3": 0
                                },
                                {
                                    "perk": 8321,
                                    "var1": 2,
                                    "var2": 0,
                                    "var3": 0
                                }
                            ],
                            "style": 8300
                        }
                    ]
                },
                "physicalDamageDealt": 1304,
                "physicalDamageDealtToChampions": 403,
                "physicalDamageTaken": 22542,
                "profileIcon": 654,
                "puuid": "EE5aE_cUHRK3Jtybd8n5FTH1Yx_zosqTAV_yscfg4TdGufm8jc6Fs99eVMxBEeVMAeJnI7MqGvWU0Q",
                "quadraKills": 0,
                "riotIdName": "",
                "riotIdTagline": "",
                "role": "SUPPORT",
                "sightWardsBoughtInGame": 0,
                "spell1Casts": 76,
                "spell2Casts": 79,
                "spell3Casts": 50,
                "spell4Casts": 12,
                "summoner1Casts": 4,
                "summoner1Id": 4,
                "summoner2Casts": 3,
                "summoner2Id": 7,
                "summonerId": "q6r5y97IdIuW8MIU_8Dy8XCCyYO33cpY-mRRyuqSO0GHPw",
                "summonerLevel": 58,
                "summonerName": "Ablon29",
                "teamEarlySurrendered": false,
                "teamId": 200,
                "teamPosition": "",
                "timeCCingOthers": 29,
                "timePlayed": 1260,
                "totalDamageDealt": 50546,
                "totalDamageDealtToChampions": 16413,
                "totalDamageShieldedOnTeammates": 0,
                "totalDamageTaken": 23993,
                "totalHeal": 1805,
                "totalHealsOnTeammates": 180,
                "totalMinionsKilled": 39,
                "totalTimeCCDealt": 153,
                "totalTimeSpentDead": 338,
                "totalUnitsHealed": 3,
                "tripleKills": 0,
                "trueDamageDealt": 2470,
                "trueDamageDealtToChampions": 0,
                "trueDamageTaken": 569,
                "turretKills": 0,
                "turretTakedowns": 0,
                "turretsLost": 4,
                "unrealKills": 0,
                "visionScore": 0,
                "visionWardsBoughtInGame": 0,
                "wardsKilled": 0,
                "wardsPlaced": 0,
                "win": false
            },
            {
                "assists": 19,
                "baronKills": 0,
                "bountyLevel": 0,
                "champExperience": 20154,
                "champLevel": 18,
                "championId": 34,
                "championName": "Anivia",
                "championTransform": 0,
                "consumablesPurchased": 2,
                "damageDealtToBuildings": 994,
                "damageDealtToObjectives": 994,
                "damageDealtToTurrets": 994,
                "damageSelfMitigated": 16290,
                "deaths": 14,
                "detectorWardsPlaced": 0,
                "doubleKills": 1,
                "dragonKills": 0,
                "firstBloodAssist": false,
                "firstBloodKill": false,
                "firstTowerAssist": false,
                "firstTowerKill": false,
                "gameEndedInEarlySurrender": false,
                "gameEndedInSurrender": false,
                "goldEarned": 13617,
                "goldSpent": 13785,
                "individualPosition": "Invalid",
                "inhibitorKills": 0,
                "inhibitorTakedowns": 0,
                "inhibitorsLost": 1,
                "item0": 6653,
                "item1": 3040,
                "item2": 3020,
                "item3": 4637,
                "item4": 3165,
                "item5": 1052,
                "item6": 2052,
                "itemsPurchased": 19,
                "killingSprees": 2,
                "kills": 8,
                "lane": "TOP",
                "largestCriticalStrike": 0,
                "largestKillingSpree": 3,
                "largestMultiKill": 3,
                "longestTimeSpentLiving": 176,
                "magicDamageDealt": 64918,
                "magicDamageDealtToChampions": 19412,
                "magicDamageTaken": 2069,
                "neutralMinionsKilled": 0,
                "nexusKills": 0,
                "nexusLost": 1,
                "nexusTakedowns": 0,
                "objectivesStolen": 0,
                "objectivesStolenAssists": 0,
                "participantId": 7,
                "pentaKills": 0,
                "perks": {
                    "statPerks": {
                        "defense": 5001,
                        "flex": 5008,
                        "offense": 5008
                    },
                    "styles": [
                        {
                            "description": "primaryStyle",
                            "selections": [
                                {
                                    "perk": 8128,
                                    "var1": 1636,
                                    "var2": 27,
                                    "var3": 0
                                },
                                {
                                    "perk": 8126,
                                    "var1": 1111,
                                    "var2": 0,
                                    "var3": 0
                                },
                                {
                                    "perk": 8138,
                                    "var1": 30,
                                    "var2": 0,
                                    "var3": 0
                                },
                                {
                                    "perk": 8135,
                                    "var1": 1447,
                                    "var2": 5,
                                    "var3": 0
                                }
                            ],
                            "style": 8100
                        },
                        {
                            "description": "subStyle",
                            "selections": [
                                {
                                    "perk": 8009,
                                    "var1": 5250,
                                    "var2": 0,
                                    "var3": 0
                                },
                                {
                                    "perk": 8014,
                                    "var1": 701,
                                    "var2": 0,
                                    "var3": 0
                                }
                            ],
                            "style": 8000
                        }
                    ]
                },
                "physicalDamageDealt": 3735,
                "physicalDamageDealtToChampions": 997,
                "physicalDamageTaken": 32402,
                "profileIcon": 940,
                "puuid": "GNly6iOMNVfvlYRkqCjp7FGp8g2HAKYFBl5MGnH-_opTrJtNu1HF7VOMDFiKzx9rYDp1ACFxoeNo9w",
                "quadraKills": 0,
                "riotIdName": "",
                "riotIdTagline": "",
                "role": "SUPPORT",
                "sightWardsBoughtInGame": 0,
                "spell1Casts": 85,
                "spell2Casts": 28,
                "spell3Casts": 42,
                "spell4Casts": 57,
                "summoner1Casts": 4,
                "summoner1Id": 4,
                "summoner2Casts": 7,
                "summoner2Id": 21,
                "summonerId": "_96UE8T3M6KP-Qsr8nE-zF4zWj9k0q9sezXOqkp8Fg47DQc",
                "summonerLevel": 79,
                "summonerName": "Flaming Gator",
                "teamEarlySurrendered": false,
                "teamId": 200,
                "teamPosition": "",
                "timeCCingOthers": 44,
                "timePlayed": 1260,
                "totalDamageDealt": 74614,
                "totalDamageDealtToChampions": 21341,
                "totalDamageShieldedOnTeammates": 0,
                "totalDamageTaken": 35531,
                "totalHeal": 2388,
                "totalHealsOnTeammates": 0,
                "totalMinionsKilled": 64,
                "totalTimeCCDealt": 585,
                "totalTimeSpentDead": 334,
                "totalUnitsHealed": 1,
                "tripleKills": 1,
                "trueDamageDealt": 5961,
                "trueDamageDealtToChampions": 931,
                "trueDamageTaken": 1059,
                "turretKills": 0,
                "turretTakedowns": 1,
                "turretsLost": 4,
                "unrealKills": 0,
                "visionScore": 0,
                "visionWardsBoughtInGame": 0,
                "wardsKilled": 0,
                "wardsPlaced": 0,
                "win": false
            },
            {
                "assists": 23,
                "baronKills": 0,
                "bountyLevel": 0,
                "champExperience": 20039,
                "champLevel": 18,
                "championId": 134,
                "championName": "Syndra",
                "championTransform": 0,
                "consumablesPurchased": 2,
                "damageDealtToBuildings": 1093,
                "damageDealtToObjectives": 1093,
                "damageDealtToTurrets": 1093,
                "damageSelfMitigated": 13204,
                "deaths": 8,
                "detectorWardsPlaced": 0,
                "doubleKills": 2,
                "dragonKills": 0,
                "firstBloodAssist": false,
                "firstBloodKill": false,
                "firstTowerAssist": false,
                "firstTowerKill": false,
                "gameEndedInEarlySurrender": false,
                "gameEndedInSurrender": false,
                "goldEarned": 14051,
                "goldSpent": 13200,
                "individualPosition": "Invalid",
                "inhibitorKills": 0,
                "inhibitorTakedowns": 0,
                "inhibitorsLost": 1,
                "item0": 6655,
                "item1": 3020,
                "item2": 3089,
                "item3": 3157,
                "item4": 3102,
                "item5": 0,
                "item6": 2052,
                "itemsPurchased": 19,
                "killingSprees": 2,
                "kills": 9,
                "lane": "TOP",
                "largestCriticalStrike": 0,
                "largestKillingSpree": 5,
                "largestMultiKill": 2,
                "longestTimeSpentLiving": 288,
                "magicDamageDealt": 65615,
                "magicDamageDealtToChampions": 18320,
                "magicDamageTaken": 816,
                "neutralMinionsKilled": 0,
                "nexusKills": 0,
                "nexusLost": 1,
                "nexusTakedowns": 0,
                "objectivesStolen": 0,
                "objectivesStolenAssists": 0,
                "participantId": 8,
                "pentaKills": 0,
                "perks": {
                    "statPerks": {
                        "defense": 5001,
                        "flex": 5008,
                        "offense": 5008
                    },
                    "styles": [
                        {
                            "description": "primaryStyle",
                            "selections": [
                                {
                                    "perk": 8229,
                                    "var1": 1736,
                                    "var2": 0,
                                    "var3": 0
                                },
                                {
                                    "perk": 8226,
                                    "var1": 250,
                                    "var2": 861,
                                    "var3": 0
                                },
                                {
                                    "perk": 8210,
                                    "var1": 21,
                                    "var2": 0,
                                    "var3": 0
                                },
                                {
                                    "perk": 8236,
                                    "var1": 48,
                                    "var2": 0,
                                    "var3": 0
                                }
                            ],
                            "style": 8200
                        },
                        {
                            "description": "subStyle",
                            "selections": [
                                {
                                    "perk": 8138,
                                    "var1": 30,
                                    "var2": 0,
                                    "var3": 0
                                },
                                {
                                    "perk": 8105,
                                    "var1": 13,
                                    "var2": 5,
                                    "var3": 0
                                }
                            ],
                            "style": 8100
                        }
                    ]
                },
                "physicalDamageDealt": 2614,
                "physicalDamageDealtToChampions": 675,
                "physicalDamageTaken": 17295,
                "profileIcon": 5091,
                "puuid": "66NyRlrbkqV4S1IlflA7b7gtR9bdaikAWSbXsmaq6iua0k1oj25DlprwUIS3qZmHIo7Stf6aI64fIw",
                "quadraKills": 0,
                "riotIdName": "",
                "riotIdTagline": "",
                "role": "SUPPORT",
                "sightWardsBoughtInGame": 0,
                "spell1Casts": 82,
                "spell2Casts": 104,
                "spell3Casts": 39,
                "spell4Casts": 4,
                "summoner1Casts": 3,
                "summoner1Id": 4,
                "summoner2Casts": 3,
                "summoner2Id": 7,
                "summonerId": "cRWnt0D0w8yiAaxFUmnH-sxdeFcSl-st-2dZdh8uid7HhQ",
                "summonerLevel": 57,
                "summonerName": "Lindethiel",
                "teamEarlySurrendered": false,
                "teamId": 200,
                "teamPosition": "",
                "timeCCingOthers": 36,
                "timePlayed": 1260,
                "totalDamageDealt": 69118,
                "totalDamageDealtToChampions": 19199,
                "totalDamageShieldedOnTeammates": 0,
                "totalDamageTaken": 18426,
                "totalHeal": 2132,
                "totalHealsOnTeammates": 120,
                "totalMinionsKilled": 62,
                "totalTimeCCDealt": 180,
                "totalTimeSpentDead": 212,
                "totalUnitsHealed": 3,
                "tripleKills": 0,
                "trueDamageDealt": 888,
                "trueDamageDealtToChampions": 203,
                "trueDamageTaken": 314,
                "turretKills": 1,
                "turretTakedowns": 1,
                "turretsLost": 4,
                "unrealKills": 0,
                "visionScore": 0,
                "visionWardsBoughtInGame": 0,
                "wardsKilled": 0,
                "wardsPlaced": 0,
                "win": false
            },
            {
                "assists": 18,
                "baronKills": 0,
                "bountyLevel": 0,
                "champExperience": 22419,
                "champLevel": 18,
                "championId": 142,
                "championName": "Zoe",
                "championTransform": 0,
                "consumablesPurchased": 3,
                "damageDealtToBuildings": 490,
                "damageDealtToObjectives": 490,
                "damageDealtToTurrets": 490,
                "damageSelfMitigated": 13839,
                "deaths": 11,
                "detectorWardsPlaced": 0,
                "doubleKills": 4,
                "dragonKills": 0,
                "firstBloodAssist": false,
                "firstBloodKill": false,
                "firstTowerAssist": false,
                "firstTowerKill": false,
                "gameEndedInEarlySurrender": false,
                "gameEndedInSurrender": false,
                "goldEarned": 15834,
                "goldSpent": 14700,
                "individualPosition": "Invalid",
                "inhibitorKills": 0,
                "inhibitorTakedowns": 0,
                "inhibitorsLost": 1,
                "item0": 3157,
                "item1": 3020,
                "item2": 3089,
                "item3": 3135,
                "item4": 6655,
                "item5": 3916,
                "item6": 2052,
                "itemsPurchased": 15,
                "killingSprees": 5,
                "kills": 18,
                "lane": "TOP",
                "largestCriticalStrike": 0,
                "largestKillingSpree": 5,
                "largestMultiKill": 2,
                "longestTimeSpentLiving": 284,
                "magicDamageDealt": 44033,
                "magicDamageDealtToChampions": 23994,
                "magicDamageTaken": 2195,
                "neutralMinionsKilled": 0,
                "nexusKills": 0,
                "nexusLost": 1,
                "nexusTakedowns": 0,
                "objectivesStolen": 0,
                "objectivesStolenAssists": 0,
                "participantId": 9,
                "pentaKills": 0,
                "perks": {
                    "statPerks": {
                        "defense": 5002,
                        "flex": 5008,
                        "offense": 5008
                    },
                    "styles": [
                        {
                            "description": "primaryStyle",
                            "selections": [
                                {
                                    "perk": 8128,
                                    "var1": 2442,
                                    "var2": 28,
                                    "var3": 0
                                },
                                {
                                    "perk": 8126,
                                    "var1": 563,
                                    "var2": 0,
                                    "var3": 0
                                },
                                {
                                    "perk": 8138,
                                    "var1": 30,
                                    "var2": 0,
                                    "var3": 0
                                },
                                {
                                    "perk": 8135,
                                    "var1": 1716,
                                    "var2": 5,
                                    "var3": 0
                                }
                            ],
                            "style": 8100
                        },
                        {
                            "description": "subStyle",
                            "selections": [
                                {
                                    "perk": 8009,
                                    "var1": 3788,
                                    "var2": 0,
                                    "var3": 0
                                },
                                {
                                    "perk": 8014,
                                    "var1": 913,
                                    "var2": 0,
                                    "var3": 0
                                }
                            ],
                            "style": 8000
                        }
                    ]
                },
                "physicalDamageDealt": 4617,
                "physicalDamageDealtToChampions": 1914,
                "physicalDamageTaken": 22736,
                "profileIcon": 4552,
                "puuid": "UW3X7SlXHsN2YaQPT-nVc2qgj4AtcpQiBKz2ypwifdhnfumz5LhZDuW8X86OGZIjyx3shpXuTkJkXA",
                "quadraKills": 0,
                "riotIdName": "",
                "riotIdTagline": "",
                "role": "SUPPORT",
                "sightWardsBoughtInGame": 0,
                "spell1Casts": 129,
                "spell2Casts": 24,
                "spell3Casts": 47,
                "spell4Casts": 26,
                "summoner1Casts": 6,
                "summoner1Id": 7,
                "summoner2Casts": 4,
                "summoner2Id": 4,
                "summonerId": "jV1s6UW6kY2iystErxHUEehj-EmmeY8KoSvuXj-YLv3isQ",
                "summonerLevel": 204,
                "summonerName": "OMEGAROLL",
                "teamEarlySurrendered": false,
                "teamId": 200,
                "teamPosition": "",
                "timeCCingOthers": 33,
                "timePlayed": 1260,
                "totalDamageDealt": 51588,
                "totalDamageDealtToChampions": 28702,
                "totalDamageShieldedOnTeammates": 0,
                "totalDamageTaken": 25226,
                "totalHeal": 3241,
                "totalHealsOnTeammates": 607,
                "totalMinionsKilled": 34,
                "totalTimeCCDealt": 116,
                "totalTimeSpentDead": 290,
                "totalUnitsHealed": 4,
                "tripleKills": 0,
                "trueDamageDealt": 2937,
                "trueDamageDealtToChampions": 2793,
                "trueDamageTaken": 294,
                "turretKills": 0,
                "turretTakedowns": 1,
                "turretsLost": 4,
                "unrealKills": 0,
                "visionScore": 0,
                "visionWardsBoughtInGame": 0,
                "wardsKilled": 0,
                "wardsPlaced": 0,
                "win": false
            },
            {
                "assists": 13,
                "baronKills": 0,
                "bountyLevel": 0,
                "champExperience": 17482,
                "champLevel": 17,
                "championId": 84,
                "championName": "Akali",
                "championTransform": 0,
                "consumablesPurchased": 7,
                "damageDealtToBuildings": 185,
                "damageDealtToObjectives": 185,
                "damageDealtToTurrets": 185,
                "damageSelfMitigated": 22149,
                "deaths": 12,
                "detectorWardsPlaced": 0,
                "doubleKills": 0,
                "dragonKills": 0,
                "firstBloodAssist": false,
                "firstBloodKill": false,
                "firstTowerAssist": false,
                "firstTowerKill": false,
                "gameEndedInEarlySurrender": false,
                "gameEndedInSurrender": false,
                "goldEarned": 13300,
                "goldSpent": 11950,
                "individualPosition": "Invalid",
                "inhibitorKills": 0,
                "inhibitorTakedowns": 0,
                "inhibitorsLost": 1,
                "item0": 1001,
                "item1": 4633,
                "item2": 3102,
                "item3": 3135,
                "item4": 3075,
                "item5": 0,
                "item6": 2052,
                "itemsPurchased": 23,
                "killingSprees": 1,
                "kills": 11,
                "lane": "MIDDLE",
                "largestCriticalStrike": 12,
                "largestKillingSpree": 4,
                "largestMultiKill": 1,
                "longestTimeSpentLiving": 240,
                "magicDamageDealt": 23413,
                "magicDamageDealtToChampions": 12394,
                "magicDamageTaken": 1371,
                "neutralMinionsKilled": 0,
                "nexusKills": 0,
                "nexusLost": 1,
                "nexusTakedowns": 0,
                "objectivesStolen": 0,
                "objectivesStolenAssists": 0,
                "participantId": 10,
                "pentaKills": 0,
                "perks": {
                    "statPerks": {
                        "defense": 5002,
                        "flex": 5008,
                        "offense": 5008
                    },
                    "styles": [
                        {
                            "description": "primaryStyle",
                            "selections": [
                                {
                                    "perk": 8010,
                                    "var1": 191,
                                    "var2": 0,
                                    "var3": 0
                                },
                                {
                                    "perk": 8009,
                                    "var1": 623,
                                    "var2": 0,
                                    "var3": 0
                                },
                                {
                                    "perk": 9105,
                                    "var1": 6,
                                    "var2": 20,
                                    "var3": 0
                                },
                                {
                                    "perk": 8014,
                                    "var1": 568,
                                    "var2": 0,
                                    "var3": 0
                                }
                            ],
                            "style": 8000
                        },
                        {
                            "description": "subStyle",
                            "selections": [
                                {
                                    "perk": 8139,
                                    "var1": 946,
                                    "var2": 0,
                                    "var3": 0
                                },
                                {
                                    "perk": 8135,
                                    "var1": 864,
                                    "var2": 5,
                                    "var3": 0
                                }
                            ],
                            "style": 8100
                        }
                    ]
                },
                "physicalDamageDealt": 2910,
                "physicalDamageDealtToChampions": 1487,
                "physicalDamageTaken": 28525,
                "profileIcon": 4829,
                "puuid": "eLT_SnTzJWb0T3VYMkrY3tkhbKg5mguEJjZZhh-Gn8Wp5YflPy_zS1pxKnpY-JQjnTMCKzJkJOYjSg",
                "quadraKills": 0,
                "riotIdName": "",
                "riotIdTagline": "",
                "role": "SOLO",
                "sightWardsBoughtInGame": 0,
                "spell1Casts": 61,
                "spell2Casts": 17,
                "spell3Casts": 41,
                "spell4Casts": 7,
                "summoner1Casts": 0,
                "summoner1Id": 4,
                "summoner2Casts": 19,
                "summoner2Id": 32,
                "summonerId": "5CWtgr3kAjodmCgAdDXfTRoZ_8icThZWTzfRDKgtGgJVOw",
                "summonerLevel": 77,
                "summonerName": "crazy mofo",
                "teamEarlySurrendered": false,
                "teamId": 200,
                "teamPosition": "",
                "timeCCingOthers": 0,
                "timePlayed": 1260,
                "totalDamageDealt": 47667,
                "totalDamageDealtToChampions": 15449,
                "totalDamageShieldedOnTeammates": 0,
                "totalDamageTaken": 30550,
                "totalHeal": 1946,
                "totalHealsOnTeammates": 0,
                "totalMinionsKilled": 11,
                "totalTimeCCDealt": 11,
                "totalTimeSpentDead": 272,
                "totalUnitsHealed": 1,
                "tripleKills": 0,
                "trueDamageDealt": 21342,
                "trueDamageDealtToChampions": 1567,
                "trueDamageTaken": 653,
                "turretKills": 0,
                "turretTakedowns": 0,
                "turretsLost": 4,
                "unrealKills": 0,
                "visionScore": 0,
                "visionWardsBoughtInGame": 0,
                "wardsKilled": 0,
                "wardsPlaced": 0,
                "win": false
            }
        ],
        "platformId": "BR1",
        "queueId": 450,
        "teams": [
            {
                "bans": [],
                "objectives": {
                    "baron": {
                        "first": false,
                        "kills": 0
                    },
                    "champion": {
                        "first": true,
                        "kills": 57
                    },
                    "dragon": {
                        "first": false,
                        "kills": 0
                    },
                    "inhibitor": {
                        "first": true,
                        "kills": 1
                    },
                    "riftHerald": {
                        "first": false,
                        "kills": 0
                    },
                    "tower": {
                        "first": true,
                        "kills": 4
                    }
                },
                "teamId": 100,
                "win": true
            },
            {
                "bans": [],
                "objectives": {
                    "baron": {
                        "first": false,
                        "kills": 0
                    },
                    "champion": {
                        "first": false,
                        "kills": 51
                    },
                    "dragon": {
                        "first": false,
                        "kills": 0
                    },
                    "inhibitor": {
                        "first": false,
                        "kills": 0
                    },
                    "riftHerald": {
                        "first": false,
                        "kills": 0
                    },
                    "tower": {
                        "first": false,
                        "kills": 1
                    }
                },
                "teamId": 200,
                "win": false
            }
        ],
        "tournamentCode": ""
    }
}